{
    "data_uri": "/data/example_wp_log_peyton_manning.csv",
    "train_uri": "/data/models/full/train.csv",
    "output_uri": "/data/models/full/output.csv",
    "model_uri": "/data/models/full/model.pickle",
    "holidays_input_uri": null,
    "holidays_output_uri": null,
    "delimiter": ",",
    "ds": "ds",
    "y": "y",
    "ts_frequency": "D",
    "min_train_date": null,
    "max_train_date": null,
    "saturating_min": null,
    "saturating_max": null,
    "na_fill": null,
    "random_seed": 1234,
    "country_holidays": null,
    "custom_seasonalities": [
        {
            "name": "monthly",
            "period": 30.5,
            "fourier_order": 5
        }
    ],
    "growth": "linear",
    "changepoints": null,
    "n_changepoints": 25,
    "changepoint_range": 0.8,
    "yearly_seasonality": "auto",
    "weekly_seasonality": "auto",
    "daily_seasonality": "auto",
    "holidays": null,
    "seasonality_mode": "additive",
    "seasonality_prior_scale": 10.0,
    "holidays_prior_scale": 10.0,
    "changepoint_prior_scale": 0.05,
    "mcmc_samples": 0,
    "interval_width": 0.8,
    "uncertainty_samples": 1000,
    "stan_backend": null
}